codeprompt/__init__.py
codeprompt/__main__.py
llfmt/__init__.py
llfmt/__main__.py
llmfmt-2024.1.22.dist-info/LICENSE
llmfmt-2024.1.22.dist-info/METADATA
llmfmt-2024.1.22.dist-info/WHEEL
llmfmt-2024.1.22.dist-info/entry_points.txt
llmfmt-2024.1.22.dist-info/top_level.txt
llmfmt-2024.1.22.dist-info/RECORD
